topsis_sneha_102303033/__init__.py
topsis_sneha_102303033/core.py
topsis_sneha_102303033-0.1.1.dist-info/METADATA
topsis_sneha_102303033-0.1.1.dist-info/WHEEL
topsis_sneha_102303033-0.1.1.dist-info/top_level.txt
topsis_sneha_102303033-0.1.1.dist-info/RECORD
