Metadata-Version: 2.4
Name: Topsis-sneha-102303033
Version: 0.1.1
Summary: TOPSIS implementation for multi-criteria decision making
Author-email: Your Name <you@example.com>
License: MIT
Requires-Python: >=3.8
Requires-Dist: pandas>=1.5.0
Requires-Dist: numpy>=1.24.0
